tzero.py
tzero-0.2.0.dist-info/LICENSE.md
tzero-0.2.0.dist-info/METADATA
tzero-0.2.0.dist-info/WHEEL
tzero-0.2.0.dist-info/entry_points.txt
tzero-0.2.0.dist-info/top_level.txt
tzero-0.2.0.dist-info/RECORD
