Metadata-Version: 2.1
Name: tzero
Version: 0.2.0
Summary: Tzero - IRC timeboxing
Author: Susam Pal
License: MIT
Project-URL: homepage, https://github.com/susam/tzero
Keywords: irc,matrix,bridge,service
Classifier: Development Status :: 4 - Beta
Classifier: Environment :: Console
Classifier: Intended Audience :: End Users/Desktop
Classifier: Intended Audience :: System Administrators
Classifier: License :: OSI Approved :: MIT License
Classifier: Operating System :: OS Independent
Classifier: Programming Language :: Python :: 3
Classifier: Topic :: Internet
Classifier: Topic :: Utilities
License-File: LICENSE.md
